{"description": ["M\u00f4 T\u1ea3 C\u00f4ng Vi\u1ec7c\n             \n\n              V\u1ec1 export:\n              \n              - L\u00e0m vi\u1ec7c v\u1edbi Sales ho\u1eb7c t\u01b0 v\u1ea5n tr\u1ef1c ti\u1ebfp cho kh\u00e1ch h\u00e0ng v\u1ec1 d\u1ecbch v\u1ee5 li\u00ean quan nh\u01b0: g\u1eedi l\u1ecbch t\u00e0u,\u2026\n              \n              - Li\u00ean l\u1ea1c carrier, airline \u0111\u1ec3 l\u1ea5y gi\u00e1, l\u1ecbch t\u00e0u, l\u1ea5y booking v\u00e0 g\u1eedi cho kh\u00e1ch h\u00e0ng.\n              \n              - X\u1eed l\u00fd c\u00e1c v\u1ea5n \u0111\u1ec1 ph\u00e1t sinh li\u00ean quan nh\u01b0: l\u1ea5y cont, closing time,\u2026 \u0111\u1ea3m b\u1ea3o l\u00f4 h\u00e0ng xu\u1ea5t theo k\u1ebf ho\u1ea1ch.\n              \n              V\u1ec1 import:\n              \n              - L\u00e0m vi\u1ec7c v\u1edbi carrier, airline v\u00e0 agent nh\u1eadn ch\u1ee9ng t\u1eeb h\u00e0ng nh\u1eadp.\n              \n              - Khai e-manifest, g\u1eedi A/N, giao l\u1ec7nh v\u00e0 x\u1eed l\u00fd c\u00e1c v\u1ea5n \u0111\u1ec1 ph\u00e1t sinh li\u00ean quan.\n             \n\n              Xem to\u00e0n b\u1ed9 M\u00f4 T\u1ea3 C\u00f4ng Vi\u1ec7c"], "field": ["H\u00e0nh ch\u00e1nh/Th\u01b0 k\u00fd", "D\u1ecbch v\u1ee5 kh\u00e1ch h\u00e0ng", "Xu\u1ea5t nh\u1eadp kh\u1ea9u"], "requirement": ["Y\u00eau C\u1ea7u C\u00f4ng Vi\u1ec7c\n             \n\n              - T\u1ed1t nghi\u1ec7p \u0110H/C\u0110 chuy\u00ean ng\u00e0nh xu\u1ea5t nh\u1eadp kh\u1ea9u.\n              \n              - Kinh nghi\u1ec7m 2 \u2013 3 n\u0103m v\u1ecb tr\u00ed t\u01b0\u01a1ng \u0111\u01b0\u01a1ng.\n              \n              - Nhan nh\u1eb9n, ch\u1ecbu kh\u00f3, c\u00f3 th\u1ec3 l\u00e0m vi\u1ec7c d\u01b0\u1edbi \u00e1p l\u1ef1c cao v\u00e0 g\u1eafn b\u00f3 l\u00e2u d\u00e0i.\n              \n              - Thanh th\u1ea1o vi t\u00ednh v\u0103n ph\u00f2ng.\n              \n              - Ti\u1ebfng Anh giao ti\u1ebfp\n             \n\n              Xem to\u00e0n b\u1ed9 Y\u00eau C\u1ea7u C\u00f4ng Vi\u1ec7c"], "phuc-loi": ["C\u00e1c Ph\u00fac L\u1ee3i D\u00e0nh Cho B\u1ea1n\n             \n\n\n\n\n\n\n\n\n                L\u01b0\u01a1ng th\u01b0\u1edfng h\u1ea5p d\u1eabn\n               \n\n\n\n\n\n\n\n                C\u00e1c ch\u1ebf \u0111\u1ed9 BHYT, BHXH theo Lu\u1eadt lao \u0111\u1ed9ng hi\u1ec7n h\u00e0nh\n               \n\n\n\n\n\n\n\n                L\u00e0m vi\u1ec7c trong m\u00f4i tr\u01b0\u1eddng n\u0103ng \u0111\u1ed9ng; c\u01a1 h\u1ed9i ph\u00e1t tri\u1ec3n ngh\u1ec1 nghi\u1ec7p"], "skill": ["Customer Service", " E-manifest", " Xu\u1ea5t Nh\u1eadp Kh\u1ea9u"]}