{"description": ["M\u00f4 T\u1ea3 C\u00f4ng Vi\u1ec7c\n             \n\n              Greetings from Renesas!\n              \n              We are the world No.1 supplier of MCU/SoC, providing cutting edge solutions for global automotive customers:\n              \n              \uf0b7 Autonomous driving car\n              \n              \uf0b7 AUTOSAR (Automotive Open System Architecture)\n              \n              \uf0b7 Safe driving/ steering/ braking systems\n              \n              \uf0b7 Car infotainment & ADAS (Advanced Driver Assistance Systems)\n              \n\n              More detail is at https://www.renesas.com/en-hq/about.html.\n              \n\n              As our expansion, we are looking for talented engineers for our automotive projects at Renesas Design Vietnam\n              \n\n              Opening Projects:\n              \n\n              1. Car Infotainment and ADAS system\n              \n              \uf0b7 Port OS (Linux, Android, Integrity) and Develop Board Support Package (BSP) for Renesas Platform\n              \n              \uf0b7 Develop Multimedia library such as Graphics, Audio/video encoding/decoding, embedded Image Processing library (OpenCV)\n              \n              \uf0b7 Develop Multimedia framework (Qt, GStreamer) for Linux, Android system to support various kinds of Audio, Video formats.\n              \n              \uf0b7 Develop Proof of Concept for Car Infotainment and ADAS system\n              \n              \uf0b7 Integrate and verify Android/Linux system (Yocto, Genivi, Tizen)\n              \n              2. AUTOSAR\n              \n              \uf0b7 Join AUTOSAR (Automotive Open System Architecture) full-cycle development from design phase to system test phase, specifically on MCAL (Microcontroller Abstraction Layer) software which directly accesses Renesas on-chip microcontroller (MCU) peripheral modules and external devices that are mapped to memory. Typical examples: SPI, CAN, PWM, ADC, WDG, FLS, MCU etc. drivers.\n             \n\n              Xem to\u00e0n b\u1ed9 M\u00f4 T\u1ea3 C\u00f4ng Vi\u1ec7c"], "field": ["IT - Ph\u1ea7n m\u1ec1m", "IT-Ph\u1ea7n c\u1ee9ng/M\u1ea1ng", "C\u00f4ng ngh\u1ec7 cao"], "requirement": ["Y\u00eau C\u1ea7u C\u00f4ng Vi\u1ec7c\n             \n\n              Your Roles:\n              \n              \uf0b7 Play the role of Senior Developer in Software Development\n              \n              \uf0b7 Lead a team of SW development from 2 to 5 members\n              \n              \uf0b7 Perform Embedded Software Engineering tasks including requirement analysis, functional design, detailed design, implementation & verification\n              \n              \uf0b7 Resolve technical issues in Software Development\n              \n              \uf0b7 Train and be mentor of junior engineers in the team\n              \n              Your Qualifications:\n              \n              \uf0b7 At least 2 years\u2019 experience in Embedded Software Development\n              \n              \uf0b7 Good at C/C++ programming (experience in Assembly is a plus)\n              \n              \uf0b7 Capable of reading and understanding hardware manual\n              \n              \uf0b7 Knowledge in Java/Android/Linux is a plus.\n              \n              \uf0b7 Knowledge of Multimedia system, Graphics library, image processing or Audio/Video Codec is a plus.\n              \n              \uf0b7 Have knowledge in quality control \uf0b7 Good at English communication\n              \n\n              Your Package:\n              \n              \uf0b7 Excellent career development:\n              \n              o Cutting edge semiconductor technology\n              \n              o Promotion opportunities\n              \n              o Domestic and overseas training opportunities\n              \n              \uf0b7 Attractive package:\n              \n              o annual income (up to 7-month salary bonus/year)\n              \n              o Recognition awards\n              \n              o Allowances (commuting, overtime, lunch)\n              \n              o Insurances (obligatory & private)  o Seniority welfare (5 years, 10 years,\u2026)\n              \n              o 14+ days for annual leave\n              \n              \uf0b7 Great environment:\n              \n              o Flexible working time\n              \n              o Remote working, work at home\n              \n              o Team work\n              \n              o Fair assessment\n              \n              o Talented and friendly people\n             \n\n              Xem to\u00e0n b\u1ed9 Y\u00eau C\u1ea7u C\u00f4ng Vi\u1ec7c"], "phuc-loi": ["C\u00e1c Ph\u00fac L\u1ee3i D\u00e0nh Cho B\u1ea1n\n             \n\n\n\n\n\n\n\n\n                Comprehensive benefits plan\n               \n\n\n\n\n\n\n\n                Insurance subject to Company Policies\n               \n\n\n\n\n\n\n\n                Working environment designed"], "skill": ["C ", " C++", " Embedded"]}