{"description": ["M\u00f4 T\u1ea3 C\u00f4ng Vi\u1ec7c\n             \n\n              If you are a student or a fresh graduate who is eager to gain the very first working experience in a good environment, join our team and you will be in charge of:\n              \n\n              1. Data input - 50%\n              \n              \u2022\tConverting data from Excel to Recruitment System\n              \n              \u2022\tSupport in managing the system's data.\n              \n              1. Recruitment - 50%\n              \n              \u2022\tPosting and searching job on the website\n              \n              \u2022\tScreening CV & phone interviewing with potential candidates and arranging appointments for interviewing.\n              \n              \u2022\tInputting the candidate information to HR system\n              \n              \u2022\tAssisting Talent Acquisition team in recruiting event.\n             \n\n              Xem to\u00e0n b\u1ed9 M\u00f4 T\u1ea3 C\u00f4ng Vi\u1ec7c"], "field": ["H\u00e0nh ch\u00e1nh/Th\u01b0 k\u00fd", "M\u1edbi t\u1ed1t nghi\u1ec7p", "Nh\u00e2n s\u1ef1"], "requirement": ["Y\u00eau C\u1ea7u C\u00f4ng Vi\u1ec7c\n             \n\n              1.\tFull skill practices and applications of Microsoft Word, Excel, PowerPoint, email.\n              \n              2.\tPassionate interest in HR, especially recruitment\n              \n              3.\tExcellent communication skills in both English and Vietnamese.\n              \n              4.\tCan work full-time during the 3-month internship.\n             \n\n              Xem to\u00e0n b\u1ed9 Y\u00eau C\u1ea7u C\u00f4ng Vi\u1ec7c"], "phuc-loi": ["C\u00e1c Ph\u00fac L\u1ee3i D\u00e0nh Cho B\u1ea1n\n             \n\n\n\n\n\n\n\n\n                Training on job\n               \n\n\n\n\n\n\n\n                Full working equipment\n               \n\n\n\n\n\n\n\n                Various Events & Acitivities"], "skill": ["C\u00f3 Th\u00e1i \u0110\u1ed9 C\u1ea7u Ti\u1ebfn", " -giao Ti\u1ebfp C\u1ea9n Th\u1eadn Trong C\u00f4ng Vi\u1ec7c", " Th\u1ef1c T\u1eadp Sinh - Sinh Vi\u00ean - M\u1edbi T\u1ed1t Nghi\u1ec7p"]}