{"description": ["M\u00f4 T\u1ea3 C\u00f4ng Vi\u1ec7c\n             \n\n              - D\u1ecbch thu\u1eadt t\u00e0i li\u1ec7u\n              \n              - Phi\u00ean d\u1ecbch ti\u1ebfng H\u00e0n trong c\u00e1c cu\u1ed9c h\u1ecdp, trao \u0111\u1ed5i, th\u1ea3o lu\u1eadn\n              \n              - Th\u1ef1c hi\u1ec7n c\u00e1c c\u00f4ng vi\u1ec7c kh\u00e1c t\u1eeb qu\u1ea3n l\u00fd v\u00e0 Ban Gi\u00e1m \u0110\u1ed1c\n              \n              - Chi ti\u1ebft s\u1ebd trao \u0111\u1ed5i trong qu\u00e1 tr\u00ecnh ph\u1ecfng v\u1ea5n\n             \n\n              Xem to\u00e0n b\u1ed9 M\u00f4 T\u1ea3 C\u00f4ng Vi\u1ec7c"], "field": ["H\u00e0nh ch\u00e1nh/Th\u01b0 k\u00fd", "D\u1ecbch v\u1ee5 kh\u00e1ch h\u00e0ng", "Bi\u00ean phi\u00ean d\u1ecbch"], "requirement": ["Y\u00eau C\u1ea7u C\u00f4ng Vi\u1ec7c\n             \n\n              Y\u00eau C\u1ea7u:\n              \n              - Th\u00e0nh th\u1ea1o nghe, n\u00f3i, \u0111\u1ecdc, vi\u1ebft ti\u1ebfng H\u00e0n\n              \n              - Nhanh nh\u1eb9n, nhi\u1ec7t t\u00ecnh trong c\u00f4ng vi\u1ec7c\n              \n              - \u1ee8ng vi\u00ean t\u1eebng \u0111i du h\u1ecdc, xu\u1ea5t kh\u1ea9u lao \u0111\u1ed9ng H\u00e0n Qu\u1ed1c v\u1ec1 n\u01b0\u1edbc c\u00f3 kh\u1ea3 n\u0103ng ti\u1ebfng H\u00e0n t\u1ed1t \u0111\u1ec1u \u0111\u01b0\u1ee3c ch\u00e0o \u0111\u00f3n\n              \n\n              Quy\u1ec1n l\u1ee3i:\n              \n              -\tL\u01b0\u01a1ng th\u1ecfa thu\u1eadn theo n\u0103ng l\u1ef1c\n              \n              -\tC\u00f3 xe \u0111\u01b0a \u0111\u00f3n t\u1eeb B\u00ecnh Th\u1ea1nh \u2013 B\u00ecnh D\u01b0\u01a1ng (VSIP 1)\n              \n              -\tTh\u01b0\u1edfng n\u0103m theo k\u1ebft qu\u1ea3 kinh doanh c\u1ee7a C\u00f4ng ty v\u00e0 n\u0103ng l\u1ef1c b\u1ea3n th\u00e2n\n              \n              -\tBHXH, BHYT, BHTN, ch\u1ebf \u0111\u1ed9 ngh\u1ec9 ph\u00e9p theo lu\u1eadt \u0111\u1ecbnh\n              \n              -\tB\u1ea3o hi\u1ec3m 24/24 v\u00e0 B\u1ea3o hi\u1ec3m s\u1ee9c kh\u1ecfe\n              \n              -\t\u0110\u01b0\u1ee3c \u0111\u00e0o t\u1ea1o n\u00e2ng cao nghi\u1ec7p v\u1ee5 v\u00e0 c\u00f3 c\u01a1 h\u1ed9i th\u0103ng ti\u1ebfn trong ngh\u1ec1 nghi\u1ec7p\n              \n              -\t\u0110\u01b0\u1ee3c x\u00e9t t\u0103ng l\u01b0\u01a1ng h\u00e0ng n\u0103m theo s\u1ef1 n\u1ed7 l\u1ef1c v\u00e0 th\u00e0nh t\u00edch\n              \n              -\tM\u00f4i tr\u01b0\u1eddng l\u00e0m vi\u1ec7c th\u00e2n thi\u1ec7n\n             \n\n              Xem to\u00e0n b\u1ed9 Y\u00eau C\u1ea7u C\u00f4ng Vi\u1ec7c"], "phuc-loi": ["C\u00e1c Ph\u00fac L\u1ee3i D\u00e0nh Cho B\u1ea1n\n             \n\n\n\n\n\n\n\n\n                Th\u01b0\u1edfng n\u0103m theo k\u1ebft qu\u1ea3 kinh doanh c\u1ee7a C\u00f4ng ty v\u00e0 n\u0103ng l\u1ef1c b\u1ea3n th\u00e2n\n               \n\n\n\n\n\n\n\n                B\u1ea3o hi\u1ec3m 24/24 v\u00e0 B\u1ea3o hi\u1ec3m s\u1ee9c kh\u1ecfe\n               \n\n\n\n\n\n\n\n                C\u00f3 xe \u0111\u01b0a \u0111\u00f3n t\u1eeb B\u00ecnh Th\u1ea1nh \u2013 B\u00ecnh D\u01b0\u01a1ng (VSIP 1)"], "skill": ["Phi\u00ean D\u1ecbch - Th\u00f4ng D\u1ecbch", " D\u1ecbch Thu\u1eadt", " Th\u00e0nh Th\u1ea1o Ti\u1ebfng H\u00e0n"]}