{"description": ["M\u00f4 T\u1ea3 C\u00f4ng Vi\u1ec7c\n             \n\n              - T\u00ecm ki\u1ebfm ngu\u1ed3n cung c\u1ea5p h\u00e0ng h\u00f3a (FMCG ho\u1eb7c Fresh Food) cho h\u1ec7 th\u1ed1ng si\u00eau th\u1ecb Aeoncitimart\n              \n              - Th\u01b0\u01a1ng thuy\u1ebft, \u0111\u00e0m ph\u00e1n v\u1edbi c\u00e1c nh\u00e0 cung c\u1ea5p v\u1ec1 c\u00e1c \u0111i\u1ec1u ki\u1ec7n mua h\u00e0ng (quy c\u00e1ch ch\u1ea5t l\u01b0\u1ee3ng, ph\u01b0\u01a1ng th\u1ee9c giao nh\u1eadn, th\u1eddi h\u1ea1n giao h\u00e0ng, th\u1eddi h\u1ea1n thanh to\u00e1n, gi\u00e1 c\u1ea3,\u2026)\n              \n              - Ki\u1ec3m tra ch\u1ea5t l\u01b0\u1ee3ng \u0111\u1ea7u v\u00e0o c\u1ee7a ngu\u1ed3n th\u1ef1c ph\u1ea9m\n              \n              - Theo d\u00f5i ti\u1ebfn tr\u00ecnh b\u1ea3o qu\u1ea3n, ch\u1ebf bi\u1ebfn, cung \u1ee9ng cho h\u1ec7 th\u1ed1ng\n              \n              - Ki\u1ec3m so\u00e1t l\u01b0\u1ee3ng h\u00e0ng c\u1ea7n cung c\u1ea5p cho h\u1ec7 th\u1ed1ng.\n              \n              - T\u1ea1o gi\u00e1, v\u00e0 c\u00e1c ch\u01b0\u01a1ng tr\u00ecnh khuy\u1ebfn m\u00e3i , ch\u01b0\u01a1ng tr\u00ecnh b\u00e1n h\u00e0ng cho s\u1ea3n ph\u1ea9m\n              \n              - Li\u00ean h\u1ec7, \u0111\u00e0m ph\u00e1n, \u0111\u00e1nh gi\u00e1 h\u00e0ng ho\u00e1, \u0111\u1eb7t h\u00e0ng, v\u00e0 gi\u1ea3i quy\u1ebft c\u00e1c v\u1ea5n \u0111\u1ec1 ph\u00e1t sinh v\u1edbi c\u00e1c nh\u00e0 cung c\u1ea5p\n              \n              - Nghi\u00ean c\u1ee9u gi\u00e1 th\u1ecb tr\u01b0\u1eddng h\u00e0ng th\u00e1ng \u0111\u1ec3 c\u00f3 nh\u1eefng \u0111i\u1ec1u ch\u1ec9nh ph\u00f9 h\u1ee3p.\n              \n              - Theo d\u00f5i hi\u1ec7u qu\u1ea3 c\u1ee7a vi\u1ec7c b\u00e1n h\u00e0ng \u0111\u1ec3 ph\u00e2n b\u1ed5 h\u00e0ng h\u00f3a h\u1ee3p l\u00fd, \u0111\u1ed3ng th\u1eddi chu\u1ea9n b\u1ecb h\u00e0ng h\u00f3a d\u1ef1 tr\u00f9 h\u1ee3p l\u00fd\n              \n              - Ph\u1ed1i h\u1ee3p v\u1edbi c\u00e1c \u0111\u01a1n v\u1ecb \u0111\u1ec3 gi\u1ea3i quy\u1ebft v\u1ea5n \u0111\u1ec1 ph\u00e1t sinh trong c\u00f4ng vi\u1ec7c c\u0169ng nh\u01b0 c\u00e1c b\u1ed9 ph\u1eadn li\u00ean quan h\u1ee3p l\u00fd nh\u1ea5t.\n             \n\n              Xem to\u00e0n b\u1ed9 M\u00f4 T\u1ea3 C\u00f4ng Vi\u1ec7c"], "field": ["B\u00e1n l\u1ebb/B\u00e1n s\u1ec9", "Thu Mua/V\u1eadt T\u01b0/Cung V\u1eadn", "H\u00e0ng ti\u00eau d\u00f9ng"], "requirement": ["Y\u00eau C\u1ea7u C\u00f4ng Vi\u1ec7c\n             \n\n              Y\u00caU C\u1ea6U\n              \n              - Nam/N\u1eef t\u1eeb 28 tu\u1ed5i tr\u1edf l\u00ean.\n              \n              - Kinh nghi\u1ec7m: c\u00f3 \u00edt nh\u1ea5t 02 n\u0103m kinh nghi\u1ec7m l\u00e0m trong l\u0129nh v\u1ef1c thu mua (\u01b0u ti\u00ean \u1ee9ng vi\u00ean c\u00f3 kinh nghi\u1ec7m trong l\u0129nh v\u1ef1c su\u1ea5t \u0103n c\u00f4ng nghi\u1ec7p, nh\u00e0 h\u00e0ng, kh\u00e1ch s\u1ea1n,...)\n              \n              - Tr\u00ecnh \u0111\u1ed9 Ti\u1ebfng Nh\u1eadt N3 tr\u1edf l\u00ean, bi\u1ebft th\u00eam ti\u1ebfng Anh l\u00e0 l\u1ee3i th\u1ebf.\n              \n              - Y\u00eau c\u1ea7u b\u1eaft bu\u1ed9c ph\u1ea3i c\u00f3 t\u00ednh t\u1ec9 m\u1ec9, c\u1ea9n th\u1eadn.\n              \n              - Am hi\u1ec3u v\u1ec1 th\u1ee7 t\u1ee5c Xu\u1ea5t Nh\u1eadp kh\u1ea9u\n              \n\n              QUY\u1ec0N L\u1ee2I \u0110\u01af\u1ee2C H\u01af\u1edeNG\n              \n              - Thu nh\u1eadp: T\u1eeb 10 tri\u1ec7u tr\u1edf l\u00ean.\n              \n              - L\u00e0m vi\u1ec7c t\u1ea1i: V\u0103n ph\u00f2ng ch\u00ednh C\u00f4ng ty\n              \n              - L\u01b0\u01a1ng th\u00e1ng 13, th\u01b0\u1edfng theo hi\u1ec7u qu\u1ea3 c\u00f4ng vi\u1ec7c, th\u01b0\u1edfng L\u1ec5, T\u1ebft theo quy \u0111\u1ecbnh chung c\u1ee7a c\u00f4ng ty.\n              \n              - Ph\u1ee5 c\u1ea5p: \u0103n tr\u01b0a, c\u00f4ng t\u00e1c ph\u00ed theo quy \u0111\u1ecbnh c\u1ee7a C\u00f4ng ty.\n              \n              - B\u1ea3o hi\u1ec3m x\u00e3 h\u1ed9i, y t\u1ebf, th\u1ea5t nghi\u1ec7p theo quy \u0111\u1ecbnh\n              \n              - Ngh\u1ec9 l\u1ec5 t\u1ebft theo lu\u1eadt lao \u0111\u1ed9ng\n              \n              - Tham gia ngh\u1ec9 m\u00e1t, d\u00e3 ngo\u1ea1i\n              \n              - \u0110\u01b0\u1ee3c tham gia c\u00e1c l\u1edbp hu\u1ea5n luy\u1ec7n k\u1ef9 n\u0103ng\n              \n              - \u0110\u01b0\u1ee3c giao l\u01b0u v\u00e0 trao \u0111\u1ed5i k\u1ef9 n\u0103ng v\u1edbi c\u00e1c h\u1ec7 th\u1ed1ng b\u00e1n l\u1ebb tr\u00ean th\u1ecb tr\u01b0\u1eddng.\n             \n\n              Xem to\u00e0n b\u1ed9 Y\u00eau C\u1ea7u C\u00f4ng Vi\u1ec7c"], "phuc-loi": ["C\u00e1c Ph\u00fac L\u1ee3i D\u00e0nh Cho B\u1ea1n\n             \n\n\n\n\n\n\n\n\n                L\u01b0\u01a1ng th\u01b0\u1edfng theo quy \u0111\u1ecbnh c\u1ee7a c\u00f4ng ty\n               \n\n\n\n\n\n\n\n                Ch\u1ebf \u0111\u1ed9 b\u1ea3o hi\u1ec3m \u0111\u1ea7y \u0111\u1ee7\n               \n\n\n\n\n\n\n\n                M\u00f4i tr\u01b0\u1eddng l\u00e0m vi\u1ec7c chuy\u00ean nghi\u1ec7p"], "skill": ["Nh\u00e0 H\u00e0ng - Kh\u00e1ch S\u1ea1n", " Thu Mua", " Ti\u1ebfng Nh\u1eadt N3"]}