{"description": ["M\u00f4 T\u1ea3 C\u00f4ng Vi\u1ec7c\n             \n\n              - Ph\u1ee5 tr\u00e1ch v\u1ec1 c\u00e1c t\u00e0i kho\u1ea3n ng\u00e2n h\u00e0ng, t\u00e0i kho\u1ea3n ph\u1ea3i tr\u1ea3 v\u00e0 h\u1ed7 tr\u1ee3 K\u1ebf to\u00e1n tr\u01b0\u1edfng trong vi\u1ec7c cung c\u1ea5p th\u00f4ng tin v\u1ec1 d\u00f2ng ti\u1ec1n.\n              \n              - Ki\u1ec3m tra k\u1ef9 c\u00e1c y\u00eau c\u1ea7u thanh to\u00e1n theo ch\u00ednh s\u00e1ch thanh to\u00e1n c\u1ee7a C\u00f4ng ty v\u00e0 H\u1ec7 th\u1ed1ng Thu\u1ebf Vi\u1ec7t Nam tr\u01b0\u1edbc khi n\u1ed9p cho K\u1ebf to\u00e1n tr\u01b0\u1edfng \u0111\u1ec3 gi\u1ea3i quy\u1ebft k\u1ecbp th\u1eddi.\n              \n              - Ki\u1ec3m tra v\u00e0 \u0111\u1ed1i chi\u1ebfu v\u1edbi t\u00e0i kho\u1ea3n ng\u00e2n h\u00e0ng k\u1ecbp th\u1eddi.\n              \n              - H\u00e0ng th\u00e1ng chu\u1ea9n b\u1ecb b\u00e1o c\u00e1o\n              \n              - B\u00e1o c\u00e1o d\u00f2ng ti\u1ec1n m\u1ed7i ng\u00e0y.\n              \n              - Th\u1ef1c hi\u1ec7n theo ghi ch\u00fa ghi n\u1ee3.\n              \n\n              \u0110\u1ecba \u0111i\u1ec3m l\u00e0m vi\u1ec7c: KCN Long Th\u00e0nh, X\u00e3 Tam An, Long Th\u00e0nh, \u0110\u1ed3ng Nai\n             \n\n              Xem to\u00e0n b\u1ed9 M\u00f4 T\u1ea3 C\u00f4ng Vi\u1ec7c"], "field": ["K\u1ebf to\u00e1n", "Ki\u1ec3m to\u00e1n", "T\u00e0i ch\u00ednh/\u0110\u1ea7u t\u01b0"], "requirement": ["Y\u00eau C\u1ea7u C\u00f4ng Vi\u1ec7c\n             \n\n              - Gi\u1edbi t\u00ednh: Nam/N\u1eef\n              \n              - C\u1eed nh\u00e2n ng\u00e0nh K\u1ebf to\u00e1n / T\u00e0i ch\u00ednh\n              \n              - 01 n\u0103m kinh nghi\u1ec7m \u1edf v\u1ecb tr\u00ed t\u01b0\u01a1ng t\u1ef1\n              \n              - Giao ti\u1ebfp t\u1ed1t b\u1eb1ng ti\u1ebfng Anh\n              \n              - Chi ti\u1ebft, trung th\u1ef1c, ch\u0103m ch\u1ec9 v\u00e0 c\u1ea9n th\u1eadn\n              \n              - \u01afu ti\u00ean \u1ee9ng vi\u00ean \u0111\u00e3 s\u1eed d\u1ee5ng ph\u1ea7n m\u1ec1m SAP\n              \n\n              Vui l\u00f2ng g\u1eedi h\u1ed3 s\u01a1 b\u1eb1ng ti\u1ebfng Vi\u1ec7t v\u00e0 ti\u1ebfng Anh.\n              \n\n              Quy\u1ec1n l\u1ee3i:\n              \n              \u0110\u01b0\u1ee3c \u0111\u00e0o t\u1ea1o c\u01a1 b\u1ea3n c\u00e1c k\u1ef9 n\u0103ng l\u00e0m vi\u1ec7c v\u00e0 \u0111\u00e0o t\u1ea1o k\u1ef9 thu\u1eadt s\u1ea3n ph\u1ea9m.\n              \n              L\u00e0m vi\u1ec7c trong m\u00f4i tr\u01b0\u1eddng n\u0103ng \u0111\u1ed9ng, chuy\u00ean nghi\u1ec7p v\u00e0 c\u00f9ng chia s\u1ebb c\u00e1c gi\u00e1 tr\u1ecb.\n              \n              H\u01b0\u1edfng c\u00e1c ch\u1ebf \u0111\u1ed9 ph\u00fac l\u1ee3i , b\u1ea3o hi\u1ec3m theo quy \u0111\u1ecbnh .\n             \n\n              Xem to\u00e0n b\u1ed9 Y\u00eau C\u1ea7u C\u00f4ng Vi\u1ec7c"], "phuc-loi": ["C\u00e1c Ph\u00fac L\u1ee3i D\u00e0nh Cho B\u1ea1n\n             \n\n\n\n\n\n\n\n\n                H\u01b0\u1edfng c\u00e1c ch\u1ebf \u0111\u1ed9 ph\u00fac l\u1ee3i , b\u1ea3o hi\u1ec3m theo quy \u0111\u1ecbnh\n               \n\n\n\n\n\n\n\n                \u0110\u01b0\u1ee3c \u0111\u00e0o t\u1ea1o c\u01a1 b\u1ea3n c\u00e1c k\u1ef9 n\u0103ng l\u00e0m vi\u1ec7c v\u00e0 \u0111\u00e0o t\u1ea1o k\u1ef9 thu\u1eadt s\u1ea3n ph\u1ea9m\n               \n\n\n\n\n\n\n\n                L\u00e0m vi\u1ec7c trong m\u00f4i tr\u01b0\u1eddng n\u0103ng \u0111\u1ed9ng, chuy\u00ean nghi\u1ec7p v\u00e0 c\u00f9ng chia s\u1ebb c\u00e1c gi\u00e1 tr\u1ecb"], "skill": ["Accounting Staff", " K\u1ebf To\u00e1n T\u1ed5ng H\u1ee3p", " General Accountant"]}